{"node":{"4086555fbdc8fa0194605d3e535324fe93649e625f":{"workers":{"app/admin/uploads/[id]/page":{"moduleId":"14316","async":false}},"layer":{"app/admin/uploads/[id]/page":"rsc"},"filename":"app/admin/uploads/[id]/page.tsx","exportedName":"$$RSC_SERVER_ACTION_0"},"405782480d88f527c39dd442b27218564971c41bdb":{"workers":{"app/admin/uploads/[id]/page":{"moduleId":"14316","async":false}},"layer":{"app/admin/uploads/[id]/page":"rsc"},"filename":"app/admin/uploads/[id]/actions.ts","exportedName":"updateUpload"},"60c7140be33b7117ebe19d32adca6b9417664604e3":{"workers":{"app/page":{"moduleId":"55454","async":false}},"layer":{"app/page":"action-browser"},"filename":"app/actions.ts","exportedName":"requestEarlyAccess"},"40e1827af808de549456becdee017d7a93b5c41b80":{"workers":{"app/admin/uploads/[id]/page":{"moduleId":"74175","async":false},"app/admin/page":{"moduleId":"74175","async":false},"app/admin/quotes/[id]/page":{"moduleId":"84838","async":false}},"layer":{"app/admin/uploads/[id]/page":"action-browser","app/admin/page":"action-browser","app/admin/quotes/[id]/page":"action-browser"},"filename":"app/admin/actions.ts","exportedName":"updateQuote"},"607ba7cf9b079f3e15eae0d7e72be96950dee6f07b":{"workers":{"app/admin/uploads/[id]/page":{"moduleId":"74175","async":false},"app/admin/page":{"moduleId":"74175","async":false},"app/admin/quotes/[id]/page":{"moduleId":"84838","async":false}},"layer":{"app/admin/uploads/[id]/page":"action-browser","app/admin/page":"action-browser","app/admin/quotes/[id]/page":"action-browser"},"filename":"app/admin/actions.ts","exportedName":"createQuoteFromUploadAction"},"6087ebcee211f50cccc9d0b0b27f0d7c5020ce6422":{"workers":{"app/admin/uploads/[id]/page":{"moduleId":"74175","async":false},"app/admin/page":{"moduleId":"74175","async":false},"app/admin/quotes/[id]/page":{"moduleId":"84838","async":false}},"layer":{"app/admin/uploads/[id]/page":"action-browser","app/admin/page":"action-browser","app/admin/quotes/[id]/page":"action-browser"},"filename":"app/admin/actions.ts","exportedName":"handleQuoteFormSubmit"},"605cebdc571c80c361e6df7e8f02f5284c497daef5":{"workers":{"app/admin/quotes/[id]/page":{"moduleId":"84838","async":false}},"layer":{"app/admin/quotes/[id]/page":"action-browser"},"filename":"app/admin/quotes/[id]/actions.ts","exportedName":"postQuoteMessageAction"}},"edge":{},"encryptionKey":"XqE5Uzj47YTG+yCniFZKsLodNRVvMCv3dX9LcuS4R+s="}