{"node":{"40a16883b253ecc4b7a5fe5152b3fe13f93f00c276":{"workers":{"app/admin/uploads/[id]/page":{"moduleId":"7514","async":false}},"layer":{"app/admin/uploads/[id]/page":"rsc"},"filename":"app/admin/uploads/[id]/page.tsx","exportedName":"$$RSC_SERVER_ACTION_0"},"4057caf3e2e35e5644876c93bf16730b9a0f550925":{"workers":{"app/admin/uploads/[id]/page":{"moduleId":"7514","async":false}},"layer":{"app/admin/uploads/[id]/page":"rsc"},"filename":"app/admin/uploads/[id]/actions.ts","exportedName":"updateUpload"},"607b98630ba70126fddb8d8db0f10793eb0bbcc599":{"workers":{"app/page":{"moduleId":"40147","async":false}},"layer":{"app/page":"action-browser"},"filename":"app/actions.ts","exportedName":"requestEarlyAccess"},"40ca365a6638d6eb95e67d11de692fd2ffb2d1f5e5":{"workers":{"app/admin/quotes/[id]/page":{"moduleId":"28208","async":false}},"layer":{"app/admin/quotes/[id]/page":"action-browser"},"filename":"app/admin/actions.ts","exportedName":"updateQuote"},"608b2366f08b6c48cdd2b2af731036b9c5b6a486bd":{"workers":{"app/admin/quotes/[id]/page":{"moduleId":"28208","async":false}},"layer":{"app/admin/quotes/[id]/page":"action-browser"},"filename":"app/admin/actions.ts","exportedName":"handleQuoteFormSubmit"}},"edge":{},"encryptionKey":"7vF0FlehMzA8TqJfNjRXdWY8mzqYki0AEeQItbPmj20="}